README.md
setup.py
AlgorithmLib.egg-info/PKG-INFO
AlgorithmLib.egg-info/SOURCES.txt
AlgorithmLib.egg-info/dependency_links.txt
AlgorithmLib.egg-info/requires.txt
AlgorithmLib.egg-info/top_level.txt
algorithmLib/__init__.py
algorithmLib/commFunction.py
algorithmLib/main.py
algorithmLib/AEC_EVALUATION/ERLE_ETSIMATION.py
algorithmLib/AEC_EVALUATION/FR_ECHO_DETECT.py
algorithmLib/AEC_EVALUATION/MATCH_AEC.py
algorithmLib/AEC_EVALUATION/__init__.py
algorithmLib/AEC_MOS/__init__.py
algorithmLib/AEC_MOS/aecmos.py
algorithmLib/AGC_EVALUATION/CAL_ATTACK_RELEASE.py
algorithmLib/AGC_EVALUATION/CAL_DELAY.py
algorithmLib/AGC_EVALUATION/CAL_GAIN_TABLE.py
algorithmLib/AGC_EVALUATION/CAL_MUSIC_STABILITY.py
algorithmLib/AGC_EVALUATION/__init__.py
algorithmLib/CLIPPING_DETECTION/__init__.py
algorithmLib/CLIPPING_DETECTION/audio_clip_detection.py
algorithmLib/DLLS/ERLE_estimation.dll
algorithmLib/DLLS/ERLE_estimation.dylib
algorithmLib/DLLS/ERLE_estimation.so
algorithmLib/DLLS/PY_PESQ.dll
algorithmLib/DLLS/PY_PESQ.dylib
algorithmLib/DLLS/SC_res_retrain_220316_185754125621__ep_007.tar
algorithmLib/DLLS/agcDelay.dll
algorithmLib/DLLS/agcDelay.dylib
algorithmLib/DLLS/agcDelay.so
algorithmLib/DLLS/attackrelease.dll
algorithmLib/DLLS/attackrelease.dylib
algorithmLib/DLLS/attackrelease.so
algorithmLib/DLLS/cygwin1.dll
algorithmLib/DLLS/g160.dll
algorithmLib/DLLS/g160.dylib
algorithmLib/DLLS/g160.so
algorithmLib/DLLS/gaintable.dll
algorithmLib/DLLS/gaintable.dylib
algorithmLib/DLLS/gaintable.so
algorithmLib/DLLS/matchsig.dll
algorithmLib/DLLS/matchsig.dylib
algorithmLib/DLLS/matchsig.so
algorithmLib/DLLS/matchsig_aec.dll
algorithmLib/DLLS/matchsig_aec.dylib
algorithmLib/DLLS/matchsig_aec.so
algorithmLib/DLLS/musicStability.dll
algorithmLib/DLLS/musicStability.dylib
algorithmLib/DLLS/musicStability.so
algorithmLib/DLLS/p563.dll
algorithmLib/DLLS/p563.dylib
algorithmLib/DLLS/p563.so
algorithmLib/DLLS/pcc.dll
algorithmLib/DLLS/pcc.dylib
algorithmLib/DLLS/pcc.so
algorithmLib/DLLS/peaqb.exe
algorithmLib/DLLS/silero_vad.jit
algorithmLib/DLLS/snr_music.dll
algorithmLib/DLLS/snr_music.dylib
algorithmLib/DLLS/snr_music.so
algorithmLib/DLLS/snr_transient.dll
