Metadata-Version: 2.1
Name: AlgorithmLib
Version: 4.0.35
Summary: audio algorithms to compute and test audio quality of speech enhencement
Home-page: https://github.com/pypa/sampleproject
Author:  MA JIANLI
Author-email: majianli@corp.netease.com
License: MIT
Platform: UNKNOWN
Classifier: Programming Language :: Python :: 3
Classifier: License :: OSI Approved :: MIT License
Classifier: Operating System :: OS Independent
Requires-Python: >=3.6
